pyinterpx/Interpolation.py
pyinterpx/__init__.py
PyInterpX-0.2.3.dist-info/LICENSE
PyInterpX-0.2.3.dist-info/METADATA
PyInterpX-0.2.3.dist-info/WHEEL
PyInterpX-0.2.3.dist-info/top_level.txt
PyInterpX-0.2.3.dist-info/RECORD
