Metadata-Version: 2.1
Name: PyInterpX
Version: 0.2.3
Summary: A highly performant, GPU compatible package for higher order interpolation in PyTorch
Author: ThomasHelfer
Author-email: thomashelfer@live.de
License: MIT
Keywords: Machine learning,Pytorch,Interpolation,Higher order interpolation,3D interpolation,GPU compatible
Classifier: Development Status :: 3 - Alpha
Classifier: License :: OSI Approved :: MIT License
Classifier: Programming Language :: Python :: 3.8
Requires-Python: >=3.8
License-File: LICENSE
Requires-Dist: torch
Requires-Dist: black
Requires-Dist: pre-commit
Requires-Dist: pytest
Requires-Dist: numpy
Requires-Dist: tqdm
Requires-Dist: matplotlib
